ujson.cpython-310-x86_64-linux-gnu.so
ujson-stubs/__init__.pyi
ujson.libs/libgcc_s-0cd532bd.so.1
ujson.libs/libstdc++-5d72f927.so.6.0.33
ujson-5.11.0.dist-info/METADATA
ujson-5.11.0.dist-info/WHEEL
ujson-5.11.0.dist-info/top_level.txt
ujson-5.11.0.dist-info/RECORD
ujson-5.11.0.dist-info/licenses/LICENSE.txt
