Metadata-Version: 2.1
Name: ujson
Version: 5.11.0
Summary: Ultra fast JSON encoder and decoder for Python
Home-page: https://github.com/ultrajson/ultrajson
Download-URL: https://github.com/ultrajson/ultrajson
Author: Jonas Tarnstrom
Project-URL: Source, https://github.com/ultrajson/ultrajson
Platform: any
Classifier: Development Status :: 5 - Production/Stable
Classifier: Intended Audience :: Developers
Classifier: Programming Language :: C
Classifier: Programming Language :: Python :: 3
Classifier: Programming Language :: Python :: 3 :: Only
Classifier: Programming Language :: Python :: 3.9
Classifier: Programming Language :: Python :: 3.10
Classifier: Programming Language :: Python :: 3.11
Classifier: Programming Language :: Python :: 3.12
Classifier: Programming Language :: Python :: 3.13
Classifier: Programming Language :: Python :: 3.14
Classifier: Typing :: Typed
Requires-Python: >=3.9
License-File: LICENSE.txt
